kotti_bstable/__init__.py
kotti_bstable/__init__.pyc
kotti_bstable/fanstatic.py
kotti_bstable/fanstatic.pyc
kotti_bstable/locale/.gitkeep
kotti_bstable/static/scripts.js
kotti_bstable/static/ext/bootstrap-datepicker/.bower.json
kotti_bstable/static/ext/bootstrap-datepicker/.editorconfig
kotti_bstable/static/ext/bootstrap-datepicker/.gitignore
kotti_bstable/static/ext/bootstrap-datepicker/.travis.yml
kotti_bstable/static/ext/bootstrap-datepicker/CHANGELOG.md
kotti_bstable/static/ext/bootstrap-datepicker/CODE_OF_CONDUCT.md
kotti_bstable/static/ext/bootstrap-datepicker/CONTRIBUTING.md
kotti_bstable/static/ext/bootstrap-datepicker/Gruntfile.js
kotti_bstable/static/ext/bootstrap-datepicker/LICENSE
kotti_bstable/static/ext/bootstrap-datepicker/README.md
kotti_bstable/static/ext/bootstrap-datepicker/bower.json
kotti_bstable/static/ext/bootstrap-datepicker/composer.json
kotti_bstable/static/ext/bootstrap-datepicker/package.json
kotti_bstable/static/ext/bootstrap-datepicker/yarn.lock
kotti_bstable/static/ext/bootstrap-datepicker/.github/ISSUE_TEMPLATE.md
kotti_bstable/static/ext/bootstrap-datepicker/.github/PULL_REQUEST_TEMPLATE.md
kotti_bstable/static/ext/bootstrap-datepicker/build/build.less
kotti_bstable/static/ext/bootstrap-datepicker/build/build3.less
kotti_bstable/static/ext/bootstrap-datepicker/build/build_standalone.less
kotti_bstable/static/ext/bootstrap-datepicker/build/build_standalone3.less
kotti_bstable/static/ext/bootstrap-datepicker/dist/css/bootstrap-datepicker.css
kotti_bstable/static/ext/bootstrap-datepicker/dist/css/bootstrap-datepicker.css.map
kotti_bstable/static/ext/bootstrap-datepicker/dist/css/bootstrap-datepicker.min.css
kotti_bstable/static/ext/bootstrap-datepicker/dist/css/bootstrap-datepicker.standalone.css
kotti_bstable/static/ext/bootstrap-datepicker/dist/css/bootstrap-datepicker.standalone.css.map
kotti_bstable/static/ext/bootstrap-datepicker/dist/css/bootstrap-datepicker.standalone.min.css
kotti_bstable-1.0.2.dist-info/LICENSE.txt
kotti_bstable-1.0.2.dist-info/METADATA
kotti_bstable-1.0.2.dist-info/WHEEL
kotti_bstable-1.0.2.dist-info/entry_points.txt
kotti_bstable-1.0.2.dist-info/top_level.txt
kotti_bstable-1.0.2.dist-info/RECORD
